LICENSE
jobmatchup/__init__.py
jobmatchup/api/__init__.py
jobmatchup/api/hh_api.py
jobmatchup/api/query.py
jobmatchup/api/superjob_api.py
jobmatchup/api/vacancy_service.py
jobmatchup/configs/__init__.py
jobmatchup/configs/app_cfg.py
jobmatchup/configs/storage.py
jobmatchup/entity/__init__.py
jobmatchup/entity/api.py
jobmatchup/entity/db.py
jobmatchup/entity/hh.py
jobmatchup/entity/super_job.py
jobmatchup/entity/vacancy.py
jobmatchup/errors/__init__.py
jobmatchup/errors/errors.py
jobmatchup/storage/__init__.py
jobmatchup/storage/db.py
jobmatchup/storage/file_db.py
jobmatchup/tools/__init__.py
jobmatchup/tools/filter_vacancy.py
jobmatchup/tools/show.py
jobmatchup/tools/sort_vacancy.py
jobmatchup-0.3.2.dist-info/LICENSE
jobmatchup-0.3.2.dist-info/METADATA
jobmatchup-0.3.2.dist-info/WHEEL
jobmatchup-0.3.2.dist-info/RECORD
